setup.py
src/Hatak_Alembic.egg-info/PKG-INFO
src/Hatak_Alembic.egg-info/SOURCES.txt
src/Hatak_Alembic.egg-info/dependency_links.txt
src/Hatak_Alembic.egg-info/namespace_packages.txt
src/Hatak_Alembic.egg-info/not-zip-safe
src/Hatak_Alembic.egg-info/requires.txt
src/Hatak_Alembic.egg-info/top_level.txt
src/haplugin/__init__.py
src/haplugin/alembic/__init__.py
src/haplugin/alembic/commands.py
src/haplugin/alembic/plugin.py